nowmail/__init__.py
nowmail/api/__init__.py
nowmail/api/async_api.py
nowmail/api/sync_api.py
nowmail/core/__init__.py
nowmail/core/client.py
nowmail/core/models.py
nowmail/core/periodic_checker.py
nowmail/services/__init__.py
nowmail/services/config.py
nowmail/services/exceptions.py
nowmail/services/interfaces.py
nowmail/services/mail_service.py
nowmail-0.1.2.dist-info/METADATA
nowmail-0.1.2.dist-info/WHEEL
nowmail-0.1.2.dist-info/top_level.txt
nowmail-0.1.2.dist-info/RECORD
