Metadata-Version: 2.1
Name: nowmail
Version: 0.1.2
Summary: A powerful library for creating and managing temporary email accounts
Home-page: https://github.com/noon05/nowmail
Author: devnu
Author-email: mma140305@gmail.com
Requires-Python: >=3.6
Requires-Dist: aiohttp>=3.10.0
Requires-Dist: pydantic>=2.0.0
Requires-Dist: tenacity>=9.0.0
